CHANGES.rst
CONTRIBUTORS.rst
MANIFEST.in
README.rst
VERSION
setup.py
docs/LICENSE.GPL
docs/LICENSE.rst
docs/index.rst
src/visaplan/__init__.py
src/visaplan.plone.pdfexport.egg-info/PKG-INFO
src/visaplan.plone.pdfexport.egg-info/SOURCES.txt
src/visaplan.plone.pdfexport.egg-info/dependency_links.txt
src/visaplan.plone.pdfexport.egg-info/entry_points.txt
src/visaplan.plone.pdfexport.egg-info/namespace_packages.txt
src/visaplan.plone.pdfexport.egg-info/not-zip-safe
src/visaplan.plone.pdfexport.egg-info/requires.txt
src/visaplan.plone.pdfexport.egg-info/top_level.txt
src/visaplan/plone/__init__.py
src/visaplan/plone/pdfexport/PDFreactor.py
src/visaplan/plone/pdfexport/__init__.py
src/visaplan/plone/pdfexport/config.py
src/visaplan/plone/pdfexport/creator.py
src/visaplan/plone/pdfexport/creator.txt
src/visaplan/plone/pdfexport/utils.py
src/visaplan/plone/pdfexport/browser/__init__.py
src/visaplan/plone/pdfexport/browser/browser.py
src/visaplan/plone/pdfexport/browser/configure.zcml
src/visaplan/plone/pdfexport/browser/crumbs.py
src/visaplan/plone/pdfexport/browser/debugable.py
src/visaplan/plone/pdfexport/browser/pdf_creator.py
src/visaplan/plone/pdfexport/browser/pdf_debug.py
src/visaplan/plone/pdfexport/browser/schema.sql
src/visaplan/plone/pdfexport/browser/templates/__init__.py
src/visaplan/plone/pdfexport/browser/templates/configure.zcml
src/visaplan/plone/pdfexport/browser/templates/cookies.txt.pt
src/visaplan/plone/pdfexport/browser/templates/edit_export_profile.pt
src/visaplan/plone/pdfexport/browser/templates/export_button.pt
src/visaplan/plone/pdfexport/browser/templates/export_view.pt
src/visaplan/plone/pdfexport/browser/templates/html_main.pt
src/visaplan/plone/pdfexport/browser/templates/html_page.pt
src/visaplan/plone/pdfexport/browser/templates/html_section.pt
src/visaplan/plone/pdfexport/browser/templates/html_view.pt
src/visaplan/plone/pdfexport/browser/templates/mail_export_notify.pt
src/visaplan/plone/pdfexport/browser/templates/manage_export_profiles.pt
src/visaplan/plone/pdfexport/browser/templates/new_export_profile.pt
src/visaplan/plone/pdfexport/browser/templates/pdf_preview.pt
src/visaplan/plone/pdfexport/browser/templates/pdf_view.pt
src/visaplan/plone/pdfexport/browser/templates/view_profile.pt
src/visaplan/plone/pdfexport/browser/templates/xml_main.pt
src/visaplan/plone/pdfexport/browser/templates/xml_view.pt